kcli-99.0.202601131259.dist-info/licenses/LICENSE
kvirt/__init__.py
kvirt/baseconfig.py
kvirt/bottle.py
kvirt/cli.py
kvirt/config.py
kvirt/containerconfig.py
kvirt/defaults.py
kvirt/ekstoken.py
kvirt/examples.py
kvirt/gketoken.py
kvirt/keywords.yaml
kvirt/klist.py
kvirt/kmcp.py
kvirt/cluster/__init__.py
kvirt/cluster/sampleprovider.py
kvirt/cluster/aks/__init__.py
kvirt/cluster/aks/fake.yml
kvirt/cluster/aks/kcli_default.yml
kvirt/cluster/eks/__init__.py
kvirt/cluster/eks/fake.yml
kvirt/cluster/eks/kcli_default.yml
kvirt/cluster/gke/__init__.py
kvirt/cluster/gke/fake.yml
kvirt/cluster/gke/kcli_default.yml
kvirt/cluster/gke/kubeconfig.j2
kvirt/cluster/hypershift/99-apps.yaml
kvirt/cluster/hypershift/99-kcli-forcedns
kvirt/cluster/hypershift/99-notifications.yaml
kvirt/cluster/hypershift/Corefile
kvirt/cluster/hypershift/__init__.py
kvirt/cluster/hypershift/assisted_infra.yml
kvirt/cluster/hypershift/assisted_ingress.yml
kvirt/cluster/hypershift/assisted_ingress_service.yml.j2
kvirt/cluster/hypershift/autoapprovercron.yml
kvirt/cluster/hypershift/bmc.yml.j2
kvirt/cluster/hypershift/calico.sh.j2
kvirt/cluster/hypershift/cilium.sh.j2
kvirt/cluster/hypershift/cloud_lb_apps.yml
kvirt/cluster/hypershift/disconnected.sh
kvirt/cluster/hypershift/extras.service
kvirt/cluster/hypershift/extras.sh
kvirt/cluster/hypershift/hostedcluster.yaml
kvirt/cluster/hypershift/httpd.yaml
kvirt/cluster/hypershift/kcli_default.yml
kvirt/cluster/hypershift/kcli_plan.yml
kvirt/cluster/hypershift/kcli_plan_assisted.yml
kvirt/cluster/hypershift/keepalived.conf
kvirt/cluster/hypershift/nmstateconfig.yml.j2
kvirt/cluster/hypershift/nodepools.yaml
kvirt/cluster/hypershift/nonlocalbind.conf
kvirt/cluster/hypershift/staticpods/coredns.yml
kvirt/cluster/hypershift/staticpods/keepalived.yml
kvirt/cluster/hypershift/staticpods/mdns.yml
kvirt/cluster/k3s/__init__.py
kvirt/cluster/k3s/bootstrap.sh
kvirt/cluster/k3s/bootstrap.yml
kvirt/cluster/k3s/cloud_lb_api.yml
kvirt/cluster/k3s/ctlplanes.sh
kvirt/cluster/k3s/ctlplanes.yml
kvirt/cluster/k3s/join.sh
kcli-99.0.202601131259.dist-info/METADATA
kcli-99.0.202601131259.dist-info/WHEEL
kcli-99.0.202601131259.dist-info/entry_points.txt
kcli-99.0.202601131259.dist-info/top_level.txt
kcli-99.0.202601131259.dist-info/RECORD
